CHANGES.txt
MANIFEST.in
README.txt
development.ini
production.ini
setup.py
vame_ir/__init__.py
vame_ir/del-it.py
vame_ir/jalali.py
vame_ir/models.py
vame_ir/security.py
vame_ir/tests.py
vame_ir/views.py
vame_ir.egg-info/PKG-INFO
vame_ir.egg-info/SOURCES.txt
vame_ir.egg-info/dependency_links.txt
vame_ir.egg-info/entry_points.txt
vame_ir.egg-info/not-zip-safe
vame_ir.egg-info/requires.txt
vame_ir.egg-info/top_level.txt
vame_ir/scripts/__init__.py
vame_ir/scripts/initializedb.py
vame_ir/static/certificate_print.css
vame_ir/static/certificate_screen.css
vame_ir/static/pyramid-16x16.png
vame_ir/static/pyramid.png
vame_ir/static/theme.css
vame_ir/static/theme.min.css
vame_ir/static/countdown/flipclock.css
vame_ir/static/countdown/flipclock.js
vame_ir/static/countdown/flipclock.min.js
vame_ir/static/dist/css/bootstrap-rtl.css
vame_ir/static/dist/css/bootstrap-rtl.min.css
vame_ir/static/dist/css/bootstrap-theme.css
vame_ir/static/dist/css/bootstrap-theme.min.css
vame_ir/static/dist/css/bootstrap.css
vame_ir/static/dist/css/bootstrap.min.css
vame_ir/static/dist/js/bootstrap.js
vame_ir/static/dist/js/bootstrap.min.js
vame_ir/static/dist/js/holder.js
vame_ir/static/dist/js/html5shiv.js
vame_ir/static/dist/js/jquery.min.js
vame_ir/static/dist/js/npm.js
vame_ir/static/dist/js/respond.min.js
vame_ir/templates/certificate.pt
vame_ir/templates/course_add.pt
vame_ir/templates/course_list.pt
vame_ir/templates/course_page.pt
vame_ir/templates/error.pt
vame_ir/templates/exam_list.pt
vame_ir/templates/exam_page.pt
vame_ir/templates/home.pt
vame_ir/templates/login.pt
vame_ir/templates/logout.pt
vame_ir/templates/main.pt
vame_ir/templates/menu.pt
vame_ir/templates/payment.pt
vame_ir/templates/profile.pt
vame_ir/templates/question_add.pt
vame_ir/templates/question_group_add.pt
vame_ir/templates/quiz_finish.pt
vame_ir/templates/quiz_question.pt
vame_ir/templates/quiz_result.pt
vame_ir/templates/quiz_start.pt
vame_ir/templates/score_exam_list.pt
vame_ir/templates/score_exam_page.pt
vame_ir/templates/signup.pt